{
   "Title":"F1InsertTests.F1InsertPerformance1ToN-20220419-025320",
   "HostEnvironmentInfo":{
      "BenchmarkDotNetCaption":"BenchmarkDotNet",
      "BenchmarkDotNetVersion":"0.13.1",
      "OsVersion":"Windows 10.0.22000",
      "ProcessorName":"12th Gen Intel Core i5-12600K",
      "PhysicalProcessorCount":1,
      "PhysicalCoreCount":10,
      "LogicalCoreCount":16,
      "RuntimeVersion":".NET 6.0.1 (6.0.121.56705)",
      "Architecture":"X64",
      "HasAttachedDebugger":false,
      "HasRyuJit":true,
      "Configuration":"RELEASE",
      "DotNetCliVersion":"6.0.101",
      "ChronometerFrequency":{
         "Hertz":10000000
      },
      "HardwareTimerKind":"Unknown"
   },
   "Benchmarks":[
      {
         "DisplayInfo":"F1InsertPerformance1ToN.InsertData: Job-IDKZER(InvocationCount=1, IterationCount=20, RunStrategy=Throughput, UnrollFactor=1, WarmupCount=20) [numberOfStatements=500]",
         "Namespace":"F1InsertTests",
         "Type":"F1InsertPerformance1ToN",
         "Method":"InsertData",
         "MethodTitle":"InsertData",
         "Parameters":"numberOfStatements=500",
         "FullName":"F1InsertTests.F1InsertPerformance1ToN.InsertData(numberOfStatements: 500)",
         "Statistics":{
            "OriginalValues":[
               1305374500,1315009300,1303732000,1307975900,1312137800,1292211800,1301688800,1298815200,1304913500,1293469800,1305188200,1321122700,1293296500,1281030000,1272932700,1289865200,1285181100,1295728400,1293643700
            ],
            "N":19,
            "Min":1272932700,
            "LowerFence":1273963350,
            "Q1":1292754150,
            "Median":1298815200,
            "Mean":1298595636.8421052,
            "Q3":1305281350,
            "UpperFence":1324072150,
            "Max":1321122700,
            "InterquartileRange":12527200,
            "LowerOutliers":[
               1272932700
            ],
            "UpperOutliers":[
               
            ],
            "AllOutliers":[
               1272932700
            ],
            "StandardError":2738476.226778716,
            "Variance":142485788848011.72,
            "StandardDeviation":11936741.131816996,
            "Skewness":-0.18292294711878784,
            "Kurtosis":2.4596785872302322,
            "ConfidenceInterval":{
               "N":19,
               "Mean":1298595636.8421052,
               "StandardError":2738476.226778716,
               "Level":12,
               "Margin":10739333.861342743,
               "Lower":1287856302.9807625,
               "Upper":1309334970.7034478
            },
            "Percentiles":{
               "P0":1272932700,
               "P25":1292754150,
               "P50":1298815200,
               "P67":1304929982,
               "P80":1306415060,
               "P85":1309224470,
               "P90":1312712100,
               "P95":1315620640,
               "P100":1321122700
            }
         },
         "Measurements":[
            {
               "IterationMode":"Overhead",
               "IterationStage":"Jitting",
               "LaunchIndex":1,
               "IterationIndex":1,
               "Operations":1,
               "Nanoseconds":149900
            },{
               "IterationMode":"Workload",
               "IterationStage":"Jitting",
               "LaunchIndex":1,
               "IterationIndex":1,
               "Operations":1,
               "Nanoseconds":12308660700
            },{
               "IterationMode":"Overhead",
               "IterationStage":"Warmup",
               "LaunchIndex":1,
               "IterationIndex":1,
               "Operations":1,
               "Nanoseconds":300
            },{
               "IterationMode":"Overhead",
               "IterationStage":"Warmup",
               "LaunchIndex":1,
               "IterationIndex":2,
               "Operations":1,
               "Nanoseconds":300
            },{
               "IterationMode":"Overhead",
               "IterationStage":"Warmup",
               "LaunchIndex":1,
               "IterationIndex":3,
               "Operations":1,
               "Nanoseconds":200
            },{
               "IterationMode":"Overhead",
               "IterationStage":"Warmup",
               "LaunchIndex":1,
               "IterationIndex":4,
               "Operations":1,
               "Nanoseconds":200
            },{
               "IterationMode":"Overhead",
               "IterationStage":"Warmup",
               "LaunchIndex":1,
               "IterationIndex":5,
               "Operations":1,
               "Nanoseconds":200
            },{
               "IterationMode":"Overhead",
               "IterationStage":"Actual",
               "LaunchIndex":1,
               "IterationIndex":1,
               "Operations":1,
               "Nanoseconds":300
            },{
               "IterationMode":"Overhead",
               "IterationStage":"Actual",
               "LaunchIndex":1,
               "IterationIndex":2,
               "Operations":1,
               "Nanoseconds":300
            },{
               "IterationMode":"Overhead",
               "IterationStage":"Actual",
               "LaunchIndex":1,
               "IterationIndex":3,
               "Operations":1,
               "Nanoseconds":200
            },{
               "IterationMode":"Overhead",
               "IterationStage":"Actual",
               "LaunchIndex":1,
               "IterationIndex":4,
               "Operations":1,
               "Nanoseconds":300
            },{
               "IterationMode":"Overhead",
               "IterationStage":"Actual",
               "LaunchIndex":1,
               "IterationIndex":5,
               "Operations":1,
               "Nanoseconds":300
            },{
               "IterationMode":"Overhead",
               "IterationStage":"Actual",
               "LaunchIndex":1,
               "IterationIndex":6,
               "Operations":1,
               "Nanoseconds":300
            },{
               "IterationMode":"Overhead",
               "IterationStage":"Actual",
               "LaunchIndex":1,
               "IterationIndex":7,
               "Operations":1,
               "Nanoseconds":200
            },{
               "IterationMode":"Overhead",
               "IterationStage":"Actual",
               "LaunchIndex":1,
               "IterationIndex":8,
               "Operations":1,
               "Nanoseconds":200
            },{
               "IterationMode":"Overhead",
               "IterationStage":"Actual",
               "LaunchIndex":1,
               "IterationIndex":9,
               "Operations":1,
               "Nanoseconds":600
            },{
               "IterationMode":"Overhead",
               "IterationStage":"Actual",
               "LaunchIndex":1,
               "IterationIndex":10,
               "Operations":1,
               "Nanoseconds":300
            },{
               "IterationMode":"Overhead",
               "IterationStage":"Actual",
               "LaunchIndex":1,
               "IterationIndex":11,
               "Operations":1,
               "Nanoseconds":200
            },{
               "IterationMode":"Overhead",
               "IterationStage":"Actual",
               "LaunchIndex":1,
               "IterationIndex":12,
               "Operations":1,
               "Nanoseconds":100
            },{
               "IterationMode":"Overhead",
               "IterationStage":"Actual",
               "LaunchIndex":1,
               "IterationIndex":13,
               "Operations":1,
               "Nanoseconds":100
            },{
               "IterationMode":"Overhead",
               "IterationStage":"Actual",
               "LaunchIndex":1,
               "IterationIndex":14,
               "Operations":1,
               "Nanoseconds":300
            },{
               "IterationMode":"Overhead",
               "IterationStage":"Actual",
               "LaunchIndex":1,
               "IterationIndex":15,
               "Operations":1,
               "Nanoseconds":200
            },{
               "IterationMode":"Overhead",
               "IterationStage":"Actual",
               "LaunchIndex":1,
               "IterationIndex":16,
               "Operations":1,
               "Nanoseconds":200
            },{
               "IterationMode":"Overhead",
               "IterationStage":"Actual",
               "LaunchIndex":1,
               "IterationIndex":17,
               "Operations":1,
               "Nanoseconds":200
            },{
               "IterationMode":"Overhead",
               "IterationStage":"Actual",
               "LaunchIndex":1,
               "IterationIndex":18,
               "Operations":1,
               "Nanoseconds":300
            },{
               "IterationMode":"Overhead",
               "IterationStage":"Actual",
               "LaunchIndex":1,
               "IterationIndex":19,
               "Operations":1,
               "Nanoseconds":200
            },{
               "IterationMode":"Overhead",
               "IterationStage":"Actual",
               "LaunchIndex":1,
               "IterationIndex":20,
               "Operations":1,
               "Nanoseconds":200
            },{
               "IterationMode":"Workload",
               "IterationStage":"Warmup",
               "LaunchIndex":1,
               "IterationIndex":1,
               "Operations":1,
               "Nanoseconds":1289698600
            },{
               "IterationMode":"Workload",
               "IterationStage":"Warmup",
               "LaunchIndex":1,
               "IterationIndex":2,
               "Operations":1,
               "Nanoseconds":1281896900
            },{
               "IterationMode":"Workload",
               "IterationStage":"Warmup",
               "LaunchIndex":1,
               "IterationIndex":3,
               "Operations":1,
               "Nanoseconds":1303922500
            },{
               "IterationMode":"Workload",
               "IterationStage":"Warmup",
               "LaunchIndex":1,
               "IterationIndex":4,
               "Operations":1,
               "Nanoseconds":1304711100
            },{
               "IterationMode":"Workload",
               "IterationStage":"Warmup",
               "LaunchIndex":1,
               "IterationIndex":5,
               "Operations":1,
               "Nanoseconds":1297253100
            },{
               "IterationMode":"Workload",
               "IterationStage":"Warmup",
               "LaunchIndex":1,
               "IterationIndex":6,
               "Operations":1,
               "Nanoseconds":1294573900
            },{
               "IterationMode":"Workload",
               "IterationStage":"Warmup",
               "LaunchIndex":1,
               "IterationIndex":7,
               "Operations":1,
               "Nanoseconds":1301671500
            },{
               "IterationMode":"Workload",
               "IterationStage":"Warmup",
               "LaunchIndex":1,
               "IterationIndex":8,
               "Operations":1,
               "Nanoseconds":1297105500
            },{
               "IterationMode":"Workload",
               "IterationStage":"Warmup",
               "LaunchIndex":1,
               "IterationIndex":9,
               "Operations":1,
               "Nanoseconds":1303333300
            },{
               "IterationMode":"Workload",
               "IterationStage":"Warmup",
               "LaunchIndex":1,
               "IterationIndex":10,
               "Operations":1,
               "Nanoseconds":1308863700
            },{
               "IterationMode":"Workload",
               "IterationStage":"Warmup",
               "LaunchIndex":1,
               "IterationIndex":11,
               "Operations":1,
               "Nanoseconds":1309130200
            },{
               "IterationMode":"Workload",
               "IterationStage":"Warmup",
               "LaunchIndex":1,
               "IterationIndex":12,
               "Operations":1,
               "Nanoseconds":1312459700
            },{
               "IterationMode":"Workload",
               "IterationStage":"Warmup",
               "LaunchIndex":1,
               "IterationIndex":13,
               "Operations":1,
               "Nanoseconds":1308480800
            },{
               "IterationMode":"Workload",
               "IterationStage":"Warmup",
               "LaunchIndex":1,
               "IterationIndex":14,
               "Operations":1,
               "Nanoseconds":1306866800
            },{
               "IterationMode":"Workload",
               "IterationStage":"Warmup",
               "LaunchIndex":1,
               "IterationIndex":15,
               "Operations":1,
               "Nanoseconds":1300621400
            },{
               "IterationMode":"Workload",
               "IterationStage":"Warmup",
               "LaunchIndex":1,
               "IterationIndex":16,
               "Operations":1,
               "Nanoseconds":1307027500
            },{
               "IterationMode":"Workload",
               "IterationStage":"Warmup",
               "LaunchIndex":1,
               "IterationIndex":17,
               "Operations":1,
               "Nanoseconds":1311810000
            },{
               "IterationMode":"Workload",
               "IterationStage":"Warmup",
               "LaunchIndex":1,
               "IterationIndex":18,
               "Operations":1,
               "Nanoseconds":1312248700
            },{
               "IterationMode":"Workload",
               "IterationStage":"Warmup",
               "LaunchIndex":1,
               "IterationIndex":19,
               "Operations":1,
               "Nanoseconds":1319175100
            },{
               "IterationMode":"Workload",
               "IterationStage":"Warmup",
               "LaunchIndex":1,
               "IterationIndex":20,
               "Operations":1,
               "Nanoseconds":1324549800
            },{
               "IterationMode":"Workload",
               "IterationStage":"Actual",
               "LaunchIndex":1,
               "IterationIndex":1,
               "Operations":1,
               "Nanoseconds":1305374700
            },{
               "IterationMode":"Workload",
               "IterationStage":"Actual",
               "LaunchIndex":1,
               "IterationIndex":2,
               "Operations":1,
               "Nanoseconds":1315009500
            },{
               "IterationMode":"Workload",
               "IterationStage":"Actual",
               "LaunchIndex":1,
               "IterationIndex":3,
               "Operations":1,
               "Nanoseconds":1303732200
            },{
               "IterationMode":"Workload",
               "IterationStage":"Actual",
               "LaunchIndex":1,
               "IterationIndex":4,
               "Operations":1,
               "Nanoseconds":1307976100
            },{
               "IterationMode":"Workload",
               "IterationStage":"Actual",
               "LaunchIndex":1,
               "IterationIndex":5,
               "Operations":1,
               "Nanoseconds":1312138000
            },{
               "IterationMode":"Workload",
               "IterationStage":"Actual",
               "LaunchIndex":1,
               "IterationIndex":6,
               "Operations":1,
               "Nanoseconds":1292212000
            },{
               "IterationMode":"Workload",
               "IterationStage":"Actual",
               "LaunchIndex":1,
               "IterationIndex":7,
               "Operations":1,
               "Nanoseconds":1301689000
            },{
               "IterationMode":"Workload",
               "IterationStage":"Actual",
               "LaunchIndex":1,
               "IterationIndex":8,
               "Operations":1,
               "Nanoseconds":1298815400
            },{
               "IterationMode":"Workload",
               "IterationStage":"Actual",
               "LaunchIndex":1,
               "IterationIndex":9,
               "Operations":1,
               "Nanoseconds":1304913700
            },{
               "IterationMode":"Workload",
               "IterationStage":"Actual",
               "LaunchIndex":1,
               "IterationIndex":10,
               "Operations":1,
               "Nanoseconds":1293470000
            },{
               "IterationMode":"Workload",
               "IterationStage":"Actual",
               "LaunchIndex":1,
               "IterationIndex":11,
               "Operations":1,
               "Nanoseconds":1305188400
            },{
               "IterationMode":"Workload",
               "IterationStage":"Actual",
               "LaunchIndex":1,
               "IterationIndex":12,
               "Operations":1,
               "Nanoseconds":1327963200
            },{
               "IterationMode":"Workload",
               "IterationStage":"Actual",
               "LaunchIndex":1,
               "IterationIndex":13,
               "Operations":1,
               "Nanoseconds":1321122900
            },{
               "IterationMode":"Workload",
               "IterationStage":"Actual",
               "LaunchIndex":1,
               "IterationIndex":14,
               "Operations":1,
               "Nanoseconds":1293296700
            },{
               "IterationMode":"Workload",
               "IterationStage":"Actual",
               "LaunchIndex":1,
               "IterationIndex":15,
               "Operations":1,
               "Nanoseconds":1281030200
            },{
               "IterationMode":"Workload",
               "IterationStage":"Actual",
               "LaunchIndex":1,
               "IterationIndex":16,
               "Operations":1,
               "Nanoseconds":1272932900
            },{
               "IterationMode":"Workload",
               "IterationStage":"Actual",
               "LaunchIndex":1,
               "IterationIndex":17,
               "Operations":1,
               "Nanoseconds":1289865400
            },{
               "IterationMode":"Workload",
               "IterationStage":"Actual",
               "LaunchIndex":1,
               "IterationIndex":18,
               "Operations":1,
               "Nanoseconds":1285181300
            },{
               "IterationMode":"Workload",
               "IterationStage":"Actual",
               "LaunchIndex":1,
               "IterationIndex":19,
               "Operations":1,
               "Nanoseconds":1295728600
            },{
               "IterationMode":"Workload",
               "IterationStage":"Actual",
               "LaunchIndex":1,
               "IterationIndex":20,
               "Operations":1,
               "Nanoseconds":1293643900
            },{
               "IterationMode":"Workload",
               "IterationStage":"Result",
               "LaunchIndex":1,
               "IterationIndex":1,
               "Operations":1,
               "Nanoseconds":1305374500
            },{
               "IterationMode":"Workload",
               "IterationStage":"Result",
               "LaunchIndex":1,
               "IterationIndex":2,
               "Operations":1,
               "Nanoseconds":1315009300
            },{
               "IterationMode":"Workload",
               "IterationStage":"Result",
               "LaunchIndex":1,
               "IterationIndex":3,
               "Operations":1,
               "Nanoseconds":1303732000
            },{
               "IterationMode":"Workload",
               "IterationStage":"Result",
               "LaunchIndex":1,
               "IterationIndex":4,
               "Operations":1,
               "Nanoseconds":1307975900
            },{
               "IterationMode":"Workload",
               "IterationStage":"Result",
               "LaunchIndex":1,
               "IterationIndex":5,
               "Operations":1,
               "Nanoseconds":1312137800
            },{
               "IterationMode":"Workload",
               "IterationStage":"Result",
               "LaunchIndex":1,
               "IterationIndex":6,
               "Operations":1,
               "Nanoseconds":1292211800
            },{
               "IterationMode":"Workload",
               "IterationStage":"Result",
               "LaunchIndex":1,
               "IterationIndex":7,
               "Operations":1,
               "Nanoseconds":1301688800
            },{
               "IterationMode":"Workload",
               "IterationStage":"Result",
               "LaunchIndex":1,
               "IterationIndex":8,
               "Operations":1,
               "Nanoseconds":1298815200
            },{
               "IterationMode":"Workload",
               "IterationStage":"Result",
               "LaunchIndex":1,
               "IterationIndex":9,
               "Operations":1,
               "Nanoseconds":1304913500
            },{
               "IterationMode":"Workload",
               "IterationStage":"Result",
               "LaunchIndex":1,
               "IterationIndex":10,
               "Operations":1,
               "Nanoseconds":1293469800
            },{
               "IterationMode":"Workload",
               "IterationStage":"Result",
               "LaunchIndex":1,
               "IterationIndex":11,
               "Operations":1,
               "Nanoseconds":1305188200
            },{
               "IterationMode":"Workload",
               "IterationStage":"Result",
               "LaunchIndex":1,
               "IterationIndex":12,
               "Operations":1,
               "Nanoseconds":1321122700
            },{
               "IterationMode":"Workload",
               "IterationStage":"Result",
               "LaunchIndex":1,
               "IterationIndex":13,
               "Operations":1,
               "Nanoseconds":1293296500
            },{
               "IterationMode":"Workload",
               "IterationStage":"Result",
               "LaunchIndex":1,
               "IterationIndex":14,
               "Operations":1,
               "Nanoseconds":1281030000
            },{
               "IterationMode":"Workload",
               "IterationStage":"Result",
               "LaunchIndex":1,
               "IterationIndex":15,
               "Operations":1,
               "Nanoseconds":1272932700
            },{
               "IterationMode":"Workload",
               "IterationStage":"Result",
               "LaunchIndex":1,
               "IterationIndex":16,
               "Operations":1,
               "Nanoseconds":1289865200
            },{
               "IterationMode":"Workload",
               "IterationStage":"Result",
               "LaunchIndex":1,
               "IterationIndex":17,
               "Operations":1,
               "Nanoseconds":1285181100
            },{
               "IterationMode":"Workload",
               "IterationStage":"Result",
               "LaunchIndex":1,
               "IterationIndex":18,
               "Operations":1,
               "Nanoseconds":1295728400
            },{
               "IterationMode":"Workload",
               "IterationStage":"Result",
               "LaunchIndex":1,
               "IterationIndex":19,
               "Operations":1,
               "Nanoseconds":1293643700
            }
         ]
      }
   ]
}
